Pythic/__init__.py
pythic-0.1.0.dist-info/METADATA
pythic-0.1.0.dist-info/WHEEL
pythic-0.1.0.dist-info/licenses/LICENSE
pythic-0.1.0.dist-info/RECORD
