Metadata-Version: 2.1
Name: Pythic
Version: 0.1.0
Summary: Just some querying functions implemented in pure C...
Author-email: Carter Canedy <cartercanedy42@gmail.com>
License-File: LICENSE
Classifier: Programming Language :: Python :: 3
Requires-Python: >=3.10
